.gitignore
CMakeLists.txt
LICENSE
README.md
pyproject.toml
setup.py
.github/workflows/python-publish.yml
examples/vicon_position.py
lib_src/vicondatastream-1.11.0/LICENSE
lib_src/vicondatastream-1.11.0/Vicon/CrossMarket/DataStream/ViconCGStream/ApexHaptics.h
lib_src/vicondatastream-1.11.0/Vicon/CrossMarket/DataStream/ViconCGStream/ApplicationInfo.h
lib_src/vicondatastream-1.11.0/Vicon/CrossMarket/DataStream/ViconCGStream/CameraCalibrationHealth.h
lib_src/vicondatastream-1.11.0/Vicon/CrossMarket/DataStream/ViconCGStream/CameraCalibrationHealthDetail.h
lib_src/vicondatastream-1.11.0/Vicon/CrossMarket/DataStream/ViconCGStream/CameraCalibrationInfo.h
lib_src/vicondatastream-1.11.0/Vicon/CrossMarket/DataStream/ViconCGStream/CameraInfo.h
lib_src/vicondatastream-1.11.0/Vicon/CrossMarket/DataStream/ViconCGStream/CameraSensorInfo.h
lib_src/vicondatastream-1.11.0/Vicon/CrossMarket/DataStream/ViconCGStream/CameraTimingInfo.h
lib_src/vicondatastream-1.11.0/Vicon/CrossMarket/DataStream/ViconCGStream/CameraWand2d.h
lib_src/vicondatastream-1.11.0/Vicon/CrossMarket/DataStream/ViconCGStream/CameraWand2dDetail.h
lib_src/vicondatastream-1.11.0/Vicon/CrossMarket/DataStream/ViconCGStream/CameraWand3d.h
lib_src/vicondatastream-1.11.0/Vicon/CrossMarket/DataStream/ViconCGStream/CameraWand3dDetail.h
lib_src/vicondatastream-1.11.0/Vicon/CrossMarket/DataStream/ViconCGStream/CentreOfPressureFrame.h
lib_src/vicondatastream-1.11.0/Vicon/CrossMarket/DataStream/ViconCGStream/CentroidTracks.h
lib_src/vicondatastream-1.11.0/Vicon/CrossMarket/DataStream/ViconCGStream/CentroidTracksDetail.h
lib_src/vicondatastream-1.11.0/Vicon/CrossMarket/DataStream/ViconCGStream/CentroidWeights.h
lib_src/vicondatastream-1.11.0/Vicon/CrossMarket/DataStream/ViconCGStream/Centroids.h
lib_src/vicondatastream-1.11.0/Vicon/CrossMarket/DataStream/ViconCGStream/CentroidsDetail.h
lib_src/vicondatastream-1.11.0/Vicon/CrossMarket/DataStream/ViconCGStream/ChannelInfo.h
pyvicon_datastream.egg-info/PKG-INFO
pyvicon_datastream.egg-info/SOURCES.txt
pyvicon_datastream.egg-info/dependency_links.txt
pyvicon_datastream.egg-info/requires.txt
pyvicon_datastream.egg-info/top_level.txt
