Metadata-Version: 2.1
Name: pyvicon-datastream
Version: 0.2.3
Summary: Platform independent Python3 wrapper for Vicon Datastream SDK
Download-URL: https://pypi.org/project/pyvicon-datastream
Author: Steffen Schmelter
Project-URL: Source Code, https://github.com/steffensc/pyvicon-datatstream-module
Platform: Windows
Platform: Linux
Platform: Mac OS-X
Platform: Unix
Requires-Python: >=3.7
License-File: LICENSE
